mccube/__init__.py
mccube/_custom_types.py
mccube/_formulae.py
mccube/_metrics.py
mccube/_path.py
mccube/_regions.py
mccube/_solvers.py
mccube/_term.py
mccube/_utils.py
mccube/_kernels/__init__.py
mccube/_kernels/base.py
mccube/_kernels/random.py
mccube/_kernels/stratified.py
mccube/_kernels/tree.py
mccube-0.0.3.dist-info/METADATA
mccube-0.0.3.dist-info/WHEEL
mccube-0.0.3.dist-info/licenses/LICENSE
mccube-0.0.3.dist-info/RECORD
