Metadata-Version: 2.1
Name: mccube
Version: 0.0.3
Summary: Markov chain cubature via JAX.
Project-URL: homepage, https://github.com/tttc3/mccube
Project-URL: documentation, https://mccube.readthedocs.io
Project-URL: repository, https://github.com/tttc3/mccube
Author-email: The MCCube team <T.Coxon2@lboro.ac.uk>
License:                                  Apache License
License-File: LICENSE
Keywords: cubature,mcmc,probability,sampling,stochastic differential equations
Classifier: Development Status :: 1 - Planning
Classifier: Intended Audience :: Developers
Classifier: Intended Audience :: Financial and Insurance Industry
Classifier: Intended Audience :: Information Technology
Classifier: Intended Audience :: Science/Research
Classifier: License :: OSI Approved :: Apache Software License
Classifier: Programming Language :: Python :: 3
Classifier: Topic :: Scientific/Engineering
Classifier: Topic :: Scientific/Engineering :: Artificial Intelligence
Classifier: Topic :: Scientific/Engineering :: Mathematics
Requires-Python: >=3.12
Requires-Dist: diffrax>=0.5.0
Requires-Dist: equinox>=0.11.2
Requires-Dist: jax>=0.4.23
Requires-Dist: jaxtyping>=0.2.25
Requires-Dist: scikit-learn>=1.3.2
Provides-Extra: dev
Requires-Dist: mccube[test]; extra == 'dev'
Requires-Dist: pre-commit; extra == 'dev'
Provides-Extra: test
Requires-Dist: beartype; extra == 'test'
Requires-Dist: jaxlib; extra == 'test'
Requires-Dist: pytest; extra == 'test'
